code_puppy/__init__.py
code_puppy/agent.py
code_puppy/agent_prompts.py
code_puppy/config.py
code_puppy/main.py
code_puppy/message_history_processor.py
code_puppy/model_factory.py
code_puppy/models.json
code_puppy/rag_async_indexer.py
code_puppy/rag_enhancer.py
code_puppy/rag_enhancer_v2.py
code_puppy/retry_handler.py
code_puppy/session_memory.py
code_puppy/state_management.py
code_puppy/tokenizer.py
code_puppy/universal_config.py
code_puppy/version_checker.py
code_puppy/command_line/__init__.py
code_puppy/command_line/file_path_completion.py
code_puppy/command_line/meta_command_handler.py
code_puppy/command_line/model_picker_completion.py
code_puppy/command_line/motd.py
code_puppy/command_line/prompt_toolkit_completion.py
code_puppy/command_line/utils.py
code_puppy/command_line/view_logs.py
code_puppy/embeddings/__init__.py
code_puppy/embeddings/batch_processor.py
code_puppy/embeddings/cache.py
code_puppy/embeddings/chunker.py
code_puppy/embeddings/config.py
code_puppy/embeddings/context_injector.py
code_puppy/embeddings/embedder.py
code_puppy/embeddings/embedder_qwen3.py
code_puppy/embeddings/embedding_manager.py
code_puppy/embeddings/embeddings_cli.py
code_puppy/embeddings/interactive_rag_config.py
code_puppy/embeddings/lightweight_client.py
code_puppy/embeddings/manager.py
code_puppy/embeddings/memory.py
code_puppy/embeddings/progress.py
code_puppy/embeddings/provider_factory.py
code_puppy/embeddings/qwen3_embedder.py
code_puppy/embeddings/rag_config_launcher.py
code_puppy/embeddings/rag_tui.py
code_puppy/embeddings/rag_tui_sync.py
code_puppy/embeddings/search.py
code_puppy/embeddings/similarity.py
code_puppy/embeddings/vector_store.py
code_puppy/embeddings/providers/__init__.py
code_puppy/embeddings/providers/base.py
code_puppy/embeddings/providers/ollama_provider.py
code_puppy/embeddings/providers/openai_compatible.py
code_puppy/embeddings/providers/openai_provider.py
code_puppy/tools/__init__.py
code_puppy/tools/command_runner.py
code_puppy/tools/common.py
swarmcode-0.1.1.dist-info/METADATA
swarmcode-0.1.1.dist-info/WHEEL
swarmcode-0.1.1.dist-info/entry_points.txt
swarmcode-0.1.1.dist-info/licenses/LICENSE
swarmcode-0.1.1.dist-info/RECORD
