Metadata-Version: 2.4
Name: swarmcode
Version: 0.1.1
Summary: Open-source AI coding assistant powered by Cerebras - fast inference for Llama 3.3 70B and Qwen3 Coder 480B
Project-URL: Homepage, https://github.com/rinadelph/swarmcode
Project-URL: Repository, https://github.com/rinadelph/swarmcode.git
Project-URL: Documentation, https://github.com/rinadelph/swarmcode#readme
Project-URL: Bug Tracker, https://github.com/rinadelph/swarmcode/issues
Project-URL: Changelog, https://github.com/rinadelph/swarmcode/releases
Author: Michael Pfaffenberger
Author-email: Luis Alejandro Rincon <alejandro@rinconnect.org>
Maintainer-email: Luis Alejandro Rincon <alejandro@rinconnect.org>
License: MIT
License-File: LICENSE
Keywords: ai,assistant,cerebras,code-generation,coding,development-tools,llama,qwen
Classifier: Development Status :: 4 - Beta
Classifier: Environment :: Console
Classifier: Intended Audience :: Developers
Classifier: License :: OSI Approved :: MIT License
Classifier: Natural Language :: English
Classifier: Operating System :: OS Independent
Classifier: Programming Language :: Python :: 3
Classifier: Programming Language :: Python :: 3.10
Classifier: Programming Language :: Python :: 3.11
Classifier: Programming Language :: Python :: 3.12
Classifier: Programming Language :: Python :: 3.13
Classifier: Topic :: Scientific/Engineering :: Artificial Intelligence
Classifier: Topic :: Software Development :: Code Generators
Classifier: Topic :: Software Development :: Libraries :: Python Modules
Requires-Python: >=3.10
Requires-Dist: bs4>=0.0.2
Requires-Dist: httpx-limiter>=0.3.0
Requires-Dist: httpx>=0.24.1
Requires-Dist: json-repair>=0.46.2
Requires-Dist: logfire>=0.7.1
Requires-Dist: pathspec>=0.11.0
Requires-Dist: prompt-toolkit>=3.0.38
Requires-Dist: pydantic-ai>=0.4.8
Requires-Dist: pydantic>=2.4.0
Requires-Dist: pytest-cov>=6.1.1
Requires-Dist: python-dotenv>=1.0.0
Requires-Dist: rapidfuzz>=3.13.0
Requires-Dist: rich>=13.4.2
Requires-Dist: ruff>=0.11.11
Requires-Dist: tree-sitter-language-pack>=0.8.0
Requires-Dist: tree-sitter-typescript>=0.23.2
Provides-Extra: dev
Requires-Dist: pytest-asyncio>=0.23.1; extra == 'dev'
Requires-Dist: pytest-cov>=6.1.1; extra == 'dev'
Requires-Dist: pytest>=8.3.4; extra == 'dev'
Requires-Dist: ruff>=0.11.11; extra == 'dev'
Provides-Extra: embeddings
Requires-Dist: numpy>=1.24.0; extra == 'embeddings'
Requires-Dist: qdrant-client>=1.7.0; extra == 'embeddings'
Requires-Dist: torch>=2.0.0; extra == 'embeddings'
Requires-Dist: transformers>=4.36.0; extra == 'embeddings'
Requires-Dist: watchdog>=3.0.0; extra == 'embeddings'
